sentry_dingding/__init__.py
sentry_dingding/forms.py
sentry_dingding/plugin.py
sentry_dingding_secret-0.11.3.dist-info/LICENSE
sentry_dingding_secret-0.11.3.dist-info/METADATA
sentry_dingding_secret-0.11.3.dist-info/WHEEL
sentry_dingding_secret-0.11.3.dist-info/entry_points.txt
sentry_dingding_secret-0.11.3.dist-info/top_level.txt
sentry_dingding_secret-0.11.3.dist-info/RECORD
