Metadata-Version: 2.1
Name: sentry-dingding-secret
Version: 0.11.3
Summary: A Sentry extension which send errors stats to DingDing
Home-page: https://github.com/ps465777545/sentry-dingding
Author: ps
Author-email: 18201403225@163.com.com
License: MIT
Keywords: sentry dingding
Platform: UNKNOWN
Classifier: Programming Language :: Python :: 2.7
Classifier: License :: OSI Approved :: MIT License
Requires-Dist: sentry (>=9.0.0)
Requires-Dist: requests
